larp/__init__.py
larp/dynamics.py
larp/field.py
larp/fn.py
larp/io.py
larp/quad.py
larp/types.py
larp-0.3.0.dist-info/licenses/LICENSE
larp-0.3.0.dist-info/METADATA
larp-0.3.0.dist-info/WHEEL
larp-0.3.0.dist-info/top_level.txt
larp-0.3.0.dist-info/RECORD
