Metadata-Version: 2.4
Name: larp
Version: 0.3.0
Summary: Larp (/lärp/): Last-Mile Restrictive Planning
Author-email: Josue N Rivera <josue.n.rivera@outlook.com>
Project-URL: Homepage, https://github.com/wzjoriv/Larp
Project-URL: Issues, https://github.com/wzjoriv/Larp/issues
Classifier: Programming Language :: Python :: 3
Classifier: Operating System :: OS Independent
License-File: LICENSE
Requires-Dist: numpy>=2.0.0
Requires-Dist: pyproj
Requires-Dist: matplotlib
Requires-Dist: scipy
Dynamic: license-file
